openapi/__init__.py
openapi/constants.py
openapi/core.py
sdk_openapi-0.0.4.dist-info/METADATA
sdk_openapi-0.0.4.dist-info/WHEEL
sdk_openapi-0.0.4.dist-info/top_level.txt
sdk_openapi-0.0.4.dist-info/RECORD
